mawo_grammar/__init__.py
mawo_grammar/checker.py
mawo_grammar/errors.py
mawo_grammar/data/rules.yml
mawo_grammar/data/rules_additional.yml
mawo_grammar/rules/__init__.py
mawo_grammar/rules/agreement.py
mawo_grammar/rules/aspect.py
mawo_grammar/rules/base.py
mawo_grammar/rules/particles.py
mawo_grammar/rules/prepositions.py
mawo_grammar/rules/yaml_loader.py
mawo_grammar-0.2.1.dist-info/licenses/LICENSE
mawo_grammar-0.2.1.dist-info/METADATA
mawo_grammar-0.2.1.dist-info/WHEEL
mawo_grammar-0.2.1.dist-info/top_level.txt
mawo_grammar-0.2.1.dist-info/RECORD
