Metadata-Version: 2.4
Name: mawo-grammar
Version: 0.2.1
Summary: Russian grammar checker with 690+ rules for professional NLP quality. Based on ЕГЭ 2025 analysis and НКРЯ corpus data
Author-email: MAWO Team <info@mawo.ru>
License-Expression: MIT
Project-URL: Homepage, https://github.com/mawo-ru/mawo-grammar
Project-URL: Repository, https://github.com/mawo-ru/mawo-grammar
Project-URL: Issues, https://github.com/mawo-ru/mawo-grammar/issues
Keywords: nlp,russian,grammar,checker,linguistic,morphology
Classifier: Development Status :: 3 - Alpha
Classifier: Intended Audience :: Developers
Classifier: Programming Language :: Python :: 3
Classifier: Programming Language :: Python :: 3.10
Classifier: Programming Language :: Python :: 3.11
Classifier: Programming Language :: Python :: 3.12
Classifier: Programming Language :: Python :: 3.13
Classifier: Topic :: Text Processing :: Linguistic
Requires-Python: >=3.10
License-File: LICENSE
Requires-Dist: mawo-pymorphy3>=1.0.4
Requires-Dist: pyyaml>=6.0.3
Provides-Extra: dev
Requires-Dist: pytest>=9.0.0; extra == "dev"
Requires-Dist: pytest-cov>=7.0.0; extra == "dev"
Requires-Dist: black>=25.11.0; extra == "dev"
Requires-Dist: ruff>=0.14.4; extra == "dev"
Requires-Dist: mypy>=1.18.2; extra == "dev"
Dynamic: license-file
